{
  "title": {
    "en": "Send notification [[msg]] with [[icon]] icon and [[color]] color for [[duration]] seconds"
  },
  "titleFormatted": {
    "en": "Send notification [[msg]] with [[icon]] icon and [[color]] color for [[duration]] seconds"
  },
  "hint": {
    "en": "Send color notification to device for specified duration with icon and color"
  },
  "args": [
    {
      "name": "device",
      "type": "device",
      "filter": "driver_id=awtrixlight"
    },
    {
      "type": "text",
      "name": "msg",
      "placeholder": {
        "en": "message"
      }
    },
    {
      "type": "dropdown",
      "name": "icon",
      "value": "-",
      "title": {
        "en": "icon"
      },
      "values": [
        {
          "id": "-",
          "title": {
            "en": "no"
          }
        },
        {
          "id": "homey",
          "title": {
            "en": "Homey"
          }
        },
        {
          "id": "heater",
          "title": {
            "en": "Heater"
          }
        },
        {
          "id": "warning",
          "title": {
            "en": "Warning"
          }
        },
        {
          "id": "lightOn",
          "title": {
            "en": "Light ON"
          }
        },
        {
          "id": "lightOff",
          "title": {
            "en": "Light Off"
          }
        },
        {
          "id": "message",
          "title": {
            "en": "Message"
          }
        },
        {
          "id": "tempC",
          "title": {
            "en": "Temp °C"
          }
        },
        {
          "id": "tempF",
          "title": {
            "en": "Temp °F"
          }
        },
        {
          "id": "smiley",
          "title": {
            "en": "Smiley"
          }
        }
      ]
    },
    {
      "type": "range",
      "name": "duration",
      "value": "5",
      "title": {
        "en": "Number of seconds"
      },
      "min": 1,
      "max": 600,
      "step": 5,
      "label": "s",
      "labelMultiplier": 1,
      "labelDecimals": 0
    },
    {
      "type": "color",
      "name": "color",
      "value": "#eeeeee"
    }
  ]
}